textual_mqtt/__about__.py
textual_mqtt/__init__.py
textual_mqtt/demo.py
textual_mqtt/textual_mqtt.py
textual_mqtt-0.0.2.dist-info/METADATA
textual_mqtt-0.0.2.dist-info/WHEEL
textual_mqtt-0.0.2.dist-info/entry_points.txt
textual_mqtt-0.0.2.dist-info/licenses/LICENSE.txt
textual_mqtt-0.0.2.dist-info/RECORD
