Metadata-Version: 2.4
Name: textual-mqtt
Version: 0.0.2
Summary: A Textual wrapper for Paho MQTT library
Project-URL: Documentation, https://github.com/marianorenzi/textual-mqtt#readme
Project-URL: Issues, https://github.com/marianorenzi/textual-mqtt/issues
Project-URL: Source, https://github.com/marianorenzi/textual-mqtt
Author-email: Mariano Renzi <mariano@renzi.com.ar>
License-Expression: MIT
License-File: LICENSE.txt
Requires-Python: >=3.8.1
Requires-Dist: paho-mqtt
Requires-Dist: textual
